BilibiliAudioDownloader/__init__.py
BilibiliAudioDownloader/audio_downloader.py
BilibiliAudioDownloader/bvid_search.py
BilibiliAudioDownloader/up_uid_search.py
bilibiliAudioDownloader-0.0.6.data/scripts/audio_downloader.py
bilibiliAudioDownloader-0.0.6.data/scripts/bvid_search.py
bilibiliAudioDownloader-0.0.6.data/scripts/up_uid_search.py
bilibiliAudioDownloader-0.0.6.dist-info/METADATA
bilibiliAudioDownloader-0.0.6.dist-info/WHEEL
bilibiliAudioDownloader-0.0.6.dist-info/entry_points.txt
bilibiliAudioDownloader-0.0.6.dist-info/top_level.txt
bilibiliAudioDownloader-0.0.6.dist-info/RECORD
