Metadata-Version: 2.1
Name: bilibiliAudioDownloader
Version: 0.0.6
Summary: A tool for downloading audio files from Bilibili videos
Home-page: https://github.com/legal-intelligence/legal-intelligence/tree/Legal_Video/BilibiliAudioDownloader
Author: YoMi__token__.21
Author-email: wanglong67890@outlook.com
License: MIT
Keywords: python,audio downloader,Bilibili
Classifier: Development Status :: 3 - Alpha
Classifier: Intended Audience :: Developers
Classifier: Programming Language :: Python :: 3
Classifier: Operating System :: OS Independent
Requires-Dist: requests
Requires-Dist: lxml
Requires-Dist: selenium
